package cn.sharesdk.framework;

import android.content.Context;
import android.graphics.Bitmap;
import android.os.Handler;
import android.os.Looper;
import android.os.Message;
import android.util.Log;
import cn.sharesdk.framework.statistics.a;
import cn.sharesdk.framework.utils.R;
import cn.sharesdk.framework.utils.d;
import cn.sharesdk.framework.utils.e;
import java.io.PrintStream;
import java.util.ArrayList;
import java.util.HashMap;
import java.util.Iterator;
import java.util.Map.Entry;
import java.util.Set;

public class p
  extends l
{
  private p.a b = p.a.a;
  private Context c;
  private HashMap<String, HashMap<String, String>> d;
  private ArrayList<Platform> e;
  private HashMap<String, Integer> f;
  private HashMap<Integer, String> g;
  private HashMap<Integer, CustomPlatform> h;
  private HashMap<Integer, HashMap<String, Object>> i;
  private HashMap<Integer, Service> j;
  private String k;
  private boolean l;
  private String m;
  private boolean n;
  private boolean o;
  
  public p(Context paramContext)
  {
    super("Thread-" + Math.abs(-22306));
    this.c = paramContext.getApplicationContext();
    e.a(this.c);
    this.d = new HashMap();
    this.e = new ArrayList();
    this.f = new HashMap();
    this.g = new HashMap();
    this.h = new HashMap();
    this.i = new HashMap();
    this.j = new HashMap();
  }
  
  private boolean a(a parama, HashMap<String, Object> paramHashMap1, HashMap<String, Object> paramHashMap2)
  {
    boolean bool2;
    try
    {
      if (paramHashMap1.containsKey("error"))
      {
        boolean bool4 = ShareSDK.isDebug();
        bool2 = false;
        if (bool4)
        {
          Log.e("ShareSDK request platform config ==>>", new d().a(paramHashMap1));
          return false;
        }
      }
      else if (!paramHashMap1.containsKey("res"))
      {
        boolean bool3 = ShareSDK.isDebug();
        bool2 = false;
        if (!bool3) {
          break label162;
        }
        Log.e("ShareSDK platform config result ==>>", "SNS configuration is empty");
        return false;
      }
    }
    catch (Throwable localThrowable)
    {
      boolean bool1 = ShareSDK.isDebug();
      bool2 = false;
      if (bool1)
      {
        localThrowable.printStackTrace();
        return false;
        String str1 = String.valueOf(paramHashMap1.get("res")).replace("\n", "");
        String str2 = parama.b(this.k, str1).trim();
        e.b("snsconf returns ===> %s", new Object[] { str2 });
        paramHashMap2.putAll(new d().a(str2));
        bool2 = true;
      }
    }
    label162:
    return bool2;
  }
  
  private void j()
  {
    for (;;)
    {
      synchronized (this.d)
      {
        this.d.clear();
        k();
        if (this.d.containsKey("ShareSDK"))
        {
          HashMap localHashMap2 = (HashMap)this.d.remove("ShareSDK");
          if (localHashMap2 != null)
          {
            if (this.k == null) {
              this.k = ((String)localHashMap2.get("AppKey"));
            }
            if (!localHashMap2.containsKey("UseVersion")) {
              break label101;
            }
            str = (String)localHashMap2.get("UseVersion");
            this.m = str;
          }
        }
        return;
      }
      label101:
      String str = "latest";
    }
  }
  
  /* Error */
  private void k()
  {
    // Byte code:
    //   0: invokestatic 206	org/xmlpull/v1/XmlPullParserFactory:newInstance	()Lorg/xmlpull/v1/XmlPullParserFactory;
    //   3: astore_3
    //   4: aload_3
    //   5: iconst_1
    //   6: invokevirtual 210	org/xmlpull/v1/XmlPullParserFactory:setNamespaceAware	(Z)V
    //   9: aload_3
    //   10: invokevirtual 214	org/xmlpull/v1/XmlPullParserFactory:newPullParser	()Lorg/xmlpull/v1/XmlPullParser;
    //   13: astore 4
    //   15: aload_0
    //   16: getfield 75	cn/sharesdk/framework/p:c	Landroid/content/Context;
    //   19: invokevirtual 218	android/content/Context:getAssets	()Landroid/content/res/AssetManager;
    //   22: ldc 220
    //   24: invokevirtual 226	android/content/res/AssetManager:open	(Ljava/lang/String;)Ljava/io/InputStream;
    //   27: astore 15
    //   29: aload 15
    //   31: astore 7
    //   33: aload 4
    //   35: aload 7
    //   37: ldc 228
    //   39: invokeinterface 234 3 0
    //   44: aload 4
    //   46: invokeinterface 238 1 0
    //   51: istore 8
    //   53: iload 8
    //   55: iconst_1
    //   56: if_icmpeq +129 -> 185
    //   59: iload 8
    //   61: iconst_2
    //   62: if_icmpne +111 -> 173
    //   65: aload 4
    //   67: invokeinterface 241 1 0
    //   72: astore 9
    //   74: new 81	java/util/HashMap
    //   77: dup
    //   78: invokespecial 82	java/util/HashMap:<init>	()V
    //   81: astore 10
    //   83: aload 4
    //   85: invokeinterface 244 1 0
    //   90: istore 11
    //   92: iconst_0
    //   93: istore 12
    //   95: iload 12
    //   97: iload 11
    //   99: if_icmpge +62 -> 161
    //   102: aload 10
    //   104: aload 4
    //   106: iload 12
    //   108: invokeinterface 248 2 0
    //   113: aload 4
    //   115: iload 12
    //   117: invokeinterface 251 2 0
    //   122: invokevirtual 168	java/lang/String:trim	()Ljava/lang/String;
    //   125: invokevirtual 255	java/util/HashMap:put	(Ljava/lang/Object;Ljava/lang/Object;)Ljava/lang/Object;
    //   128: pop
    //   129: iinc 12 1
    //   132: goto -37 -> 95
    //   135: astore 5
    //   137: aload 5
    //   139: invokestatic 258	cn/sharesdk/framework/utils/e:c	(Ljava/lang/Throwable;)I
    //   142: pop
    //   143: aload_0
    //   144: getfield 75	cn/sharesdk/framework/p:c	Landroid/content/Context;
    //   147: invokevirtual 218	android/content/Context:getAssets	()Landroid/content/res/AssetManager;
    //   150: ldc_w 260
    //   153: invokevirtual 226	android/content/res/AssetManager:open	(Ljava/lang/String;)Ljava/io/InputStream;
    //   156: astore 7
    //   158: goto -125 -> 33
    //   161: aload_0
    //   162: getfield 84	cn/sharesdk/framework/p:d	Ljava/util/HashMap;
    //   165: aload 9
    //   167: aload 10
    //   169: invokevirtual 255	java/util/HashMap:put	(Ljava/lang/Object;Ljava/lang/Object;)Ljava/lang/Object;
    //   172: pop
    //   173: aload 4
    //   175: invokeinterface 263 1 0
    //   180: istore 8
    //   182: goto -129 -> 53
    //   185: aload 7
    //   187: invokevirtual 268	java/io/InputStream:close	()V
    //   190: return
    //   191: astore_1
    //   192: aload_1
    //   193: invokestatic 258	cn/sharesdk/framework/utils/e:c	(Ljava/lang/Throwable;)I
    //   196: pop
    //   197: return
    // Local variable table:
    //   start	length	slot	name	signature
    //   0	198	0	this	p
    //   191	2	1	localThrowable1	Throwable
    //   3	7	3	localXmlPullParserFactory	org.xmlpull.v1.XmlPullParserFactory
    //   13	161	4	localXmlPullParser	org.xmlpull.v1.XmlPullParser
    //   135	3	5	localThrowable2	Throwable
    //   31	155	7	localInputStream1	java.io.InputStream
    //   51	130	8	i1	int
    //   72	94	9	str	String
    //   81	87	10	localHashMap	HashMap
    //   90	10	11	i2	int
    //   93	37	12	i3	int
    //   27	3	15	localInputStream2	java.io.InputStream
    // Exception table:
    //   from	to	target	type
    //   15	29	135	java/lang/Throwable
    //   0	15	191	java/lang/Throwable
    //   33	53	191	java/lang/Throwable
    //   65	92	191	java/lang/Throwable
    //   102	129	191	java/lang/Throwable
    //   137	158	191	java/lang/Throwable
    //   161	173	191	java/lang/Throwable
    //   173	182	191	java/lang/Throwable
    //   185	190	191	java/lang/Throwable
  }
  
  private void l()
  {
    new q(this).start();
  }
  
  private void m()
  {
    this.e.clear();
    ArrayList localArrayList = new n().a(this.c);
    if (localArrayList != null) {
      this.e.addAll(localArrayList);
    }
    synchronized (this.f)
    {
      synchronized (this.g)
      {
        Iterator localIterator = this.e.iterator();
        if (localIterator.hasNext())
        {
          Platform localPlatform = (Platform)localIterator.next();
          this.g.put(Integer.valueOf(localPlatform.getPlatformId()), localPlatform.getName());
          this.f.put(localPlatform.getName(), Integer.valueOf(localPlatform.getPlatformId()));
        }
      }
    }
  }
  
  private void n()
  {
    new n().a(this.c, this.k, this.a, this.l, e());
  }
  
  public String a(int paramInt, String paramString)
  {
    synchronized (this.i)
    {
      String str = new n().a(paramInt, paramString, this.i);
      return str;
    }
  }
  
  public String a(Bitmap paramBitmap)
  {
    if (p.a.c != this.b) {
      return null;
    }
    return new n().a(this.c, paramBitmap);
  }
  
  public String a(String paramString1, boolean paramBoolean, int paramInt, String paramString2)
  {
    if (p.a.c != this.b) {
      return paramString1;
    }
    return new n().a(this.c, this.k, paramString1, paramBoolean, paramInt, paramString2);
  }
  
  public void a()
  {
    this.b = p.a.b;
    j();
    super.a();
  }
  
  public void a(int paramInt)
  {
    cn.sharesdk.framework.network.i.a = paramInt;
  }
  
  public void a(int paramInt1, int paramInt2)
  {
    synchronized (this.i)
    {
      new n().a(paramInt1, paramInt2, this.i);
      return;
    }
  }
  
  public void a(int paramInt, Platform paramPlatform)
  {
    new n().a(paramInt, paramPlatform);
  }
  
  protected void a(Message paramMessage)
  {
    synchronized (this.e)
    {
      m();
      n();
      this.b = p.a.c;
      this.e.notify();
      l();
      return;
    }
  }
  
  public void a(Class<? extends Service> paramClass)
  {
    Service localService;
    synchronized (this.j)
    {
      if (this.j.containsKey(Integer.valueOf(paramClass.hashCode()))) {
        return;
      }
    }
  }
  
  public void a(String paramString)
  {
    this.k = paramString;
  }
  
  public void a(String paramString, int paramInt)
  {
    new n().a(paramString, paramInt);
  }
  
  public void a(String paramString1, String paramString2)
  {
    synchronized (this.d)
    {
      HashMap localHashMap2 = (HashMap)this.d.get(paramString1);
      this.d.put(paramString2, localHashMap2);
      return;
    }
  }
  
  public void a(String paramString, HashMap<String, Object> paramHashMap)
  {
    for (;;)
    {
      HashMap localHashMap2;
      synchronized (this.d)
      {
        localHashMap2 = (HashMap)this.d.get(paramString);
        if (localHashMap2 != null) {
          break label144;
        }
        synchronized (new HashMap())
        {
          Iterator localIterator = paramHashMap.entrySet().iterator();
          if (localIterator.hasNext())
          {
            Map.Entry localEntry = (Map.Entry)localIterator.next();
            String str = (String)localEntry.getKey();
            Object localObject3 = localEntry.getValue();
            if (localObject3 == null) {
              continue;
            }
            ???.put(str, String.valueOf(localObject3));
          }
        }
      }
      this.d.put(paramString, ???);
      return;
      label144:
      ??? = localHashMap2;
    }
  }
  
  public void a(boolean paramBoolean)
  {
    this.l = paramBoolean;
  }
  
  public boolean a(HashMap<String, Object> paramHashMap)
  {
    if (p.a.c != this.b)
    {
      if (ShareSDK.isDebug()) {
        System.err.println("Statistics module unopened");
      }
      return false;
    }
    a locala = a.a(this.c);
    boolean bool = a(locala, locala.e(this.k), paramHashMap);
    if (bool)
    {
      this.o = true;
      new r(this, locala).start();
      return bool;
    }
    try
    {
      String str = locala.f(this.k);
      locala.a(this.k, str);
      bool = a(locala, new d().a(str), paramHashMap);
      this.o = true;
      return bool;
    }
    catch (Throwable localThrowable)
    {
      if (ShareSDK.isDebug()) {
        localThrowable.printStackTrace();
      }
      this.o = false;
    }
    return bool;
  }
  
  public Platform b(String paramString)
  {
    if (paramString == null) {}
    for (;;)
    {
      return null;
      Platform[] arrayOfPlatform = c();
      if (arrayOfPlatform != null)
      {
        int i1 = arrayOfPlatform.length;
        for (int i2 = 0; i2 < i1; i2++)
        {
          Platform localPlatform = arrayOfPlatform[i2];
          if (paramString.equals(localPlatform.getName())) {
            return localPlatform;
          }
        }
      }
    }
  }
  
  public String b(String paramString1, String paramString2)
  {
    synchronized (this.d)
    {
      HashMap localHashMap2 = (HashMap)this.d.get(paramString1);
      if (localHashMap2 == null) {
        return null;
      }
      String str = (String)localHashMap2.get(paramString2);
      return str;
    }
  }
  
  public void b(int paramInt)
  {
    cn.sharesdk.framework.network.i.b = paramInt;
  }
  
  protected void b(Message paramMessage)
  {
    synchronized (this.j)
    {
      Iterator localIterator = this.j.entrySet().iterator();
      if (localIterator.hasNext()) {
        ((Service)((Map.Entry)localIterator.next()).getValue()).onUnbind();
      }
    }
    this.j.clear();
    synchronized (this.h)
    {
      this.h.clear();
    }
  }
  
  public void b(Class<? extends Service> paramClass)
  {
    synchronized (this.j)
    {
      int i1 = paramClass.hashCode();
      if (this.j.containsKey(Integer.valueOf(i1)))
      {
        ((Service)this.j.get(Integer.valueOf(i1))).onUnbind();
        this.j.remove(Integer.valueOf(i1));
      }
      return;
    }
  }
  
  public void b(boolean paramBoolean)
  {
    this.n = paramBoolean;
  }
  
  public boolean b(HashMap<String, Object> paramHashMap)
  {
    synchronized (this.i)
    {
      this.i.clear();
      boolean bool = new n().a(paramHashMap, this.i);
      return bool;
    }
  }
  
  public int c(String paramString)
  {
    synchronized (this.f)
    {
      if (this.f.containsKey(paramString))
      {
        int i1 = ((Integer)this.f.get(paramString)).intValue();
        return i1;
      }
      return 0;
    }
  }
  
  public <T extends Service> T c(Class<T> paramClass)
  {
    synchronized (this.j)
    {
      try
      {
        Service localService = (Service)paramClass.cast(this.j.get(Integer.valueOf(paramClass.hashCode())));
        return localService;
      }
      catch (Throwable localThrowable)
      {
        if (ShareSDK.isDebug()) {
          System.err.println(paramClass.getName() + " has not registered");
        }
        e.c(localThrowable);
        return null;
      }
    }
  }
  
  public String c(int paramInt)
  {
    synchronized (this.g)
    {
      String str = (String)this.g.get(Integer.valueOf(paramInt));
      return str;
    }
  }
  
  protected void c(Message paramMessage)
  {
    switch (paramMessage.what)
    {
    default: 
      return;
    }
    this.b = p.a.a;
    this.a.getLooper().quit();
  }
  
  public Platform[] c()
  {
    long l1 = System.currentTimeMillis();
    ArrayList localArrayList2;
    synchronized (this.e)
    {
      if (this.b == p.a.a) {
        return null;
      }
      p.a locala1 = this.b;
      p.a locala2 = p.a.b;
      if (locala1 == locala2) {}
      try
      {
        this.e.wait();
        localArrayList2 = new ArrayList();
        Iterator localIterator1 = this.e.iterator();
        while (localIterator1.hasNext())
        {
          Platform localPlatform2 = (Platform)localIterator1.next();
          if ((localPlatform2 != null) && (localPlatform2.b()))
          {
            localPlatform2.a();
            localArrayList2.add(localPlatform2);
            continue;
            localObject = finally;
          }
        }
      }
      catch (Throwable localThrowable)
      {
        for (;;)
        {
          e.c(localThrowable);
        }
      }
    }
    Iterator localIterator2 = this.h.entrySet().iterator();
    while (localIterator2.hasNext())
    {
      Platform localPlatform1 = (Platform)((Map.Entry)localIterator2.next()).getValue();
      if ((localPlatform1 != null) && (localPlatform1.b())) {
        localArrayList2.add(localPlatform1);
      }
    }
    if (localArrayList2.size() <= 0) {
      return null;
    }
    Platform[] arrayOfPlatform = new Platform[localArrayList2.size()];
    for (int i1 = 0; i1 < arrayOfPlatform.length; i1++) {
      arrayOfPlatform[i1] = ((Platform)localArrayList2.get(i1));
    }
    Object[] arrayOfObject = new Object[1];
    arrayOfObject[0] = Long.valueOf(System.currentTimeMillis() - l1);
    e.b("sort list use time: %s", arrayOfObject);
    return arrayOfPlatform;
  }
  
  public String d()
  {
    try
    {
      String str = new n().a();
      return str;
    }
    catch (Throwable localThrowable)
    {
      e.c(localThrowable);
    }
    return "2.5.7";
  }
  
  public String d(String paramString)
  {
    if (p.a.c != this.b) {
      return null;
    }
    return new n().a(this.c, paramString);
  }
  
  /* Error */
  public void d(Class<? extends CustomPlatform> paramClass)
  {
    // Byte code:
    //   0: aload_0
    //   1: getfield 95	cn/sharesdk/framework/p:h	Ljava/util/HashMap;
    //   4: astore_2
    //   5: aload_2
    //   6: monitorenter
    //   7: aload_0
    //   8: getfield 95	cn/sharesdk/framework/p:h	Ljava/util/HashMap;
    //   11: aload_1
    //   12: invokevirtual 366	java/lang/Object:hashCode	()I
    //   15: invokestatic 309	java/lang/Integer:valueOf	(I)Ljava/lang/Integer;
    //   18: invokevirtual 114	java/util/HashMap:containsKey	(Ljava/lang/Object;)Z
    //   21: ifeq +6 -> 27
    //   24: aload_2
    //   25: monitorexit
    //   26: return
    //   27: aload_1
    //   28: iconst_1
    //   29: anewarray 368	java/lang/Class
    //   32: dup
    //   33: iconst_0
    //   34: ldc 69
    //   36: aastore
    //   37: invokevirtual 513	java/lang/Class:getConstructor	([Ljava/lang/Class;)Ljava/lang/reflect/Constructor;
    //   40: astore 6
    //   42: iconst_1
    //   43: anewarray 172	java/lang/Object
    //   46: astore 7
    //   48: aload 7
    //   50: iconst_0
    //   51: aload_0
    //   52: getfield 75	cn/sharesdk/framework/p:c	Landroid/content/Context;
    //   55: aastore
    //   56: aload 6
    //   58: aload 7
    //   60: invokevirtual 518	java/lang/reflect/Constructor:newInstance	([Ljava/lang/Object;)Ljava/lang/Object;
    //   63: checkcast 520	cn/sharesdk/framework/CustomPlatform
    //   66: astore 8
    //   68: aload_0
    //   69: getfield 95	cn/sharesdk/framework/p:h	Ljava/util/HashMap;
    //   72: aload_1
    //   73: invokevirtual 366	java/lang/Object:hashCode	()I
    //   76: invokestatic 309	java/lang/Integer:valueOf	(I)Ljava/lang/Integer;
    //   79: aload 8
    //   81: invokevirtual 255	java/util/HashMap:put	(Ljava/lang/Object;Ljava/lang/Object;)Ljava/lang/Object;
    //   84: pop
    //   85: aload_0
    //   86: getfield 91	cn/sharesdk/framework/p:f	Ljava/util/HashMap;
    //   89: astore 10
    //   91: aload 10
    //   93: monitorenter
    //   94: aload_0
    //   95: getfield 93	cn/sharesdk/framework/p:g	Ljava/util/HashMap;
    //   98: astore 12
    //   100: aload 12
    //   102: monitorenter
    //   103: aload 8
    //   105: ifnull +53 -> 158
    //   108: aload 8
    //   110: invokevirtual 521	cn/sharesdk/framework/CustomPlatform:b	()Z
    //   113: ifeq +45 -> 158
    //   116: aload_0
    //   117: getfield 93	cn/sharesdk/framework/p:g	Ljava/util/HashMap;
    //   120: aload 8
    //   122: invokevirtual 522	cn/sharesdk/framework/CustomPlatform:getPlatformId	()I
    //   125: invokestatic 309	java/lang/Integer:valueOf	(I)Ljava/lang/Integer;
    //   128: aload 8
    //   130: invokevirtual 523	cn/sharesdk/framework/CustomPlatform:getName	()Ljava/lang/String;
    //   133: invokevirtual 255	java/util/HashMap:put	(Ljava/lang/Object;Ljava/lang/Object;)Ljava/lang/Object;
    //   136: pop
    //   137: aload_0
    //   138: getfield 91	cn/sharesdk/framework/p:f	Ljava/util/HashMap;
    //   141: aload 8
    //   143: invokevirtual 523	cn/sharesdk/framework/CustomPlatform:getName	()Ljava/lang/String;
    //   146: aload 8
    //   148: invokevirtual 522	cn/sharesdk/framework/CustomPlatform:getPlatformId	()I
    //   151: invokestatic 309	java/lang/Integer:valueOf	(I)Ljava/lang/Integer;
    //   154: invokevirtual 255	java/util/HashMap:put	(Ljava/lang/Object;Ljava/lang/Object;)Ljava/lang/Object;
    //   157: pop
    //   158: aload 12
    //   160: monitorexit
    //   161: aload 10
    //   163: monitorexit
    //   164: aload_2
    //   165: monitorexit
    //   166: return
    //   167: astore_3
    //   168: aload_2
    //   169: monitorexit
    //   170: aload_3
    //   171: athrow
    //   172: astore 13
    //   174: aload 12
    //   176: monitorexit
    //   177: aload 13
    //   179: athrow
    //   180: astore 11
    //   182: aload 10
    //   184: monitorexit
    //   185: aload 11
    //   187: athrow
    //   188: astore 4
    //   190: aload 4
    //   192: invokestatic 258	cn/sharesdk/framework/utils/e:c	(Ljava/lang/Throwable;)I
    //   195: pop
    //   196: goto -32 -> 164
    // Local variable table:
    //   start	length	slot	name	signature
    //   0	199	0	this	p
    //   0	199	1	paramClass	Class<? extends CustomPlatform>
    //   4	165	2	localHashMap1	HashMap
    //   167	4	3	localObject1	Object
    //   188	3	4	localThrowable	Throwable
    //   40	17	6	localConstructor	java.lang.reflect.Constructor
    //   46	13	7	arrayOfObject	Object[]
    //   66	81	8	localCustomPlatform	CustomPlatform
    //   180	6	11	localObject2	Object
    //   98	77	12	localHashMap3	HashMap
    //   172	6	13	localObject3	Object
    // Exception table:
    //   from	to	target	type
    //   7	26	167	finally
    //   27	94	167	finally
    //   164	166	167	finally
    //   168	170	167	finally
    //   185	188	167	finally
    //   190	196	167	finally
    //   108	158	172	finally
    //   158	161	172	finally
    //   174	177	172	finally
    //   94	103	180	finally
    //   161	164	180	finally
    //   177	180	180	finally
    //   182	185	180	finally
    //   27	94	188	java/lang/Throwable
    //   185	188	188	java/lang/Throwable
  }
  
  public int e()
  {
    try
    {
      int i1 = new n().b();
      return i1;
    }
    catch (Throwable localThrowable)
    {
      e.c(localThrowable);
    }
    return 48;
  }
  
  public void e(Class<? extends CustomPlatform> paramClass)
  {
    int i1 = paramClass.hashCode();
    synchronized (this.h)
    {
      this.h.remove(Integer.valueOf(i1));
      return;
    }
  }
  
  public boolean f()
  {
    return this.n;
  }
  
  public boolean g()
  {
    return this.l;
  }
  
  public boolean h()
  {
    synchronized (this.i)
    {
      if ((this.i != null) && (this.i.size() > 0)) {
        return true;
      }
      boolean bool = this.o;
      return bool;
    }
  }
  
  public void i()
  {
    try
    {
      R.clearCache(this.c);
      return;
    }
    catch (Throwable localThrowable)
    {
      e.c(localThrowable);
    }
  }
}


/* Location:           D:\15036015\反编译\shiwuku\classes_dex2jar.jar
 * Qualified Name:     cn.sharesdk.framework.p
 * JD-Core Version:    0.7.0-SNAPSHOT-20130630
 */